boringcatalog/__init__.py
boringcatalog/catalog.py
boringcatalog/cli.py
boringcatalog/duckdb_init.sql
boringcatalog-0.4.0.dist-info/METADATA
boringcatalog-0.4.0.dist-info/WHEEL
boringcatalog-0.4.0.dist-info/entry_points.txt
boringcatalog-0.4.0.dist-info/RECORD
