Metadata-Version: 2.4
Name: boringcatalog
Version: 0.4.0
Summary: A DuckDB-based Iceberg catalog implementation
Project-URL: Homepage, https://github.com/boringdata/boring-catalog
Author-email: huraultj <julien.hurault@sumeo.io>
Requires-Python: >=3.10
Requires-Dist: click>=8.0.0
Requires-Dist: duckdb>=0.9.0
Requires-Dist: pyiceberg>=0.9.0
Requires-Dist: pyiceberg[pyarrow]>=0.9.0
Requires-Dist: s3fs>=2023.12.0
Provides-Extra: test
Requires-Dist: pandas>=2.0.0; extra == 'test'
Requires-Dist: pyarrow>=14.0.0; extra == 'test'
Requires-Dist: pytest>=7.0.0; extra == 'test'
